{"symptoms":[{"id":"DUP_A","name":"dup a","patterns":["ERROR_OVERLAP"],"category":"software","severity":"P1","constraints":["C1"]},{"id":"DUP_B","name":"dup b","patterns":["ERROR_OVERLAP"],"category":"software","severity":"P2","constraints":["C1"]},{"id":"DUP_C","name":"dup c","patterns":["ERROR_OVERLAP"],"category":"software","severity":"P2","constraints":["C1"]},{"id":"WEAK_A","name":"weak a","patterns":["CRIT_DUP"],"weak_patterns":["CRIT_DUP"],"category":"software","severity":"P1","constraints":["C1"]},{"id":"WEAK_B","name":"weak b","patterns":["CRIT_DUP"],"category":"software","severity":"P1","constraints":["C1"]},{"id":"BROAD_A","name":"panic rule","patterns":["panic"],"category":"software","severity":"P2","constraints":["C1"]}]}